ZIZHUOffice365ManagementAPI_RiquelDong/ZIZHUOffice365ManagementAPI.py
ZIZHUOffice365ManagementAPI_RiquelDong/__init__.py
apacmwoffice365managementapimodule-0.0.1.dist-info/licenses/LICENSE
apacmwoffice365managementapimodule-0.0.1.dist-info/METADATA
apacmwoffice365managementapimodule-0.0.1.dist-info/WHEEL
apacmwoffice365managementapimodule-0.0.1.dist-info/top_level.txt
apacmwoffice365managementapimodule-0.0.1.dist-info/RECORD
