Metadata-Version: 2.4
Name: APACMWOffice365ManagementAPIModule
Version: 0.0.1
Summary: A small example package
Author-email: Dongli Pan <dongli.pan@microsoft.com>, Qi Dong <doqi@microsoft.com>
License-Expression: MIT
Project-URL: Homepage, https://github.com/APACMW/APACMWOffice365ManagementAPIModule
Project-URL: Issues, https://github.com/APACMW/APACMWOffice365ManagementAPIModule
Classifier: Programming Language :: Python :: 3
Classifier: Operating System :: OS Independent
Requires-Python: >=3.9
License-File: LICENSE
Dynamic: license-file
